{
  "sentences": [
    {
      "trans": "Hot unbearable",
      "orig": "ပူစပ်ပူလောင်",
      "backend": 0
    },
    {
      "src_translit": "puu hcaut puulaung"
    }
  ],
  "src": "my",
  "alternative_translations": [
    {
      "src_phrase": "ပူ",
      "alternative": [
        {
          "word_postproc": "Hot",
          "score": 999,
          "has_preceeding_space": true,
          "attach_to_next_token": false
        }
      ],
      "srcunicodeoffsets": [
        {
          "begin": 0,
          "end": 2
        }
      ],
      "raw_src_segment": "ပူစပ်ပူလောင်",
      "start_pos": 0,
      "end_pos": 1
    },
    {
      "src_phrase": "စပ် ပူလောင်",
      "alternative": [
        {
          "word_postproc": "unbearable",
          "score": 999,
          "has_preceeding_space": true,
          "attach_to_next_token": false
        }
      ],
      "srcunicodeoffsets": [
        {
          "begin": 2,
          "end": 12
        }
      ],
      "start_pos": 1,
      "end_pos": 2
    }
  ],
  "confidence": 1,
  "ld_result": {
    "srclangs": [
      "my"
    ],
    "srclangs_confidences": [
      1
    ],
    "extended_srclangs": [
      "my"
    ]
  }
}
