{
  "sentences": [
    {
      "trans": "Smartly",
      "orig": "ပြောင်ပြောင်ရောင်ရောင်",
      "backend": 0
    },
    {
      "src_translit": "pyaung pyaung raung raung"
    }
  ],
  "src": "my",
  "alternative_translations": [
    {
      "src_phrase": "ပြောင် ပြောင် ရောင် ရောင်",
      "alternative": [
        {
          "word_postproc": "Smartly",
          "score": 1000,
          "has_preceeding_space": true,
          "attach_to_next_token": false
        }
      ],
      "srcunicodeoffsets": [
        {
          "begin": 0,
          "end": 22
        }
      ],
      "raw_src_segment": "ပြောင်ပြောင်ရောင်ရောင်",
      "start_pos": 0,
      "end_pos": 1
    }
  ],
  "confidence": 1,
  "ld_result": {
    "srclangs": [
      "my"
    ],
    "srclangs_confidences": [
      1
    ],
    "extended_srclangs": [
      "my"
    ]
  }
}
