{
  "sentences": [
    {
      "trans": "Deteriorate",
      "orig": "ကြေမြည့်",
      "backend": 0
    },
    {
      "src_translit": "kyay mya ny "
    }
  ],
  "dict": [
    {
      "pos": "verb",
      "terms": [
        "deteriorate"
      ],
      "entry": [
        {
          "word": "deteriorate"
        }
      ],
      "base_form": "ကြေမြည့်",
      "pos_enum": 2
    }
  ],
  "src": "my",
  "alternative_translations": [
    {
      "src_phrase": "ကြေ မြ ည့ ်",
      "alternative": [
        {
          "word_postproc": "Deteriorate",
          "score": 1000,
          "has_preceeding_space": true,
          "attach_to_next_token": false
        }
      ],
      "srcunicodeoffsets": [
        {
          "begin": 0,
          "end": 8
        }
      ],
      "raw_src_segment": "ကြေမြည့်",
      "start_pos": 0,
      "end_pos": 1
    }
  ],
  "confidence": 1,
  "ld_result": {
    "srclangs": [
      "my"
    ],
    "srclangs_confidences": [
      1
    ],
    "extended_srclangs": [
      "my"
    ]
  }
}
