{
  "sentences": [
    {
      "trans": "barn",
      "orig": "ကျီ",
      "backend": 0
    },
    {
      "src_translit": "kyae"
    }
  ],
  "dict": [
    {
      "pos": "noun",
      "terms": [
        "barn",
        "granary: place for storing grain"
      ],
      "entry": [
        {
          "word": "barn",
          "reverse_translation": [
            "ကျီ"
          ],
          "score": 0.019803928
        }
      ],
      "base_form": "ကျီ",
      "pos_enum": 1
    }
  ],
  "src": "my",
  "alternative_translations": [
    {
      "src_phrase": "ကျီ",
      "alternative": [
        {
          "word_postproc": "barn",
          "score": 1000,
          "has_preceeding_space": true,
          "attach_to_next_token": false
        },
        {
          "word_postproc": "barns",
          "score": 0,
          "has_preceeding_space": true,
          "attach_to_next_token": false
        },
        {
          "word_postproc": "bowl when",
          "score": 0,
          "has_preceeding_space": true,
          "attach_to_next_token": false
        },
        {
          "word_postproc": "granaries",
          "score": 0,
          "has_preceeding_space": true,
          "attach_to_next_token": false
        },
        {
          "word_postproc": "bowl",
          "score": 0,
          "has_preceeding_space": true,
          "attach_to_next_token": false
        }
      ],
      "srcunicodeoffsets": [
        {
          "begin": 0,
          "end": 3
        }
      ],
      "raw_src_segment": "ကျီ",
      "start_pos": 0,
      "end_pos": 1
    }
  ],
  "confidence": 1,
  "ld_result": {
    "srclangs": [
      "my"
    ],
    "srclangs_confidences": [
      1
    ],
    "extended_srclangs": [
      "my"
    ]
  }
}
