{
  "sentences": [
    {
      "trans": "less",
      "orig": "လျော့နည်း",
      "backend": 0
    },
    {
      "src_translit": "lyawwnaee"
    }
  ],
  "dict": [
    {
      "pos": "verb",
      "terms": [
        "decrease",
        "diminish",
        "become less"
      ],
      "entry": [
        {
          "word": "decrease",
          "reverse_translation": [
            "လေျာ့ပေါ့စေ"
          ],
          "synset_id": [
            98687
          ],
          "score": 0.010435936
        }
      ],
      "base_form": "လျော့နည်း",
      "pos_enum": 2
    }
  ],
  "src": "my",
  "alternative_translations": [
    {
      "src_phrase": "လျော့နည်း",
      "alternative": [
        {
          "word_postproc": "less",
          "score": 957,
          "has_preceeding_space": true,
          "attach_to_next_token": false
        },
        {
          "word_postproc": "decreases",
          "score": 23,
          "has_preceeding_space": true,
          "attach_to_next_token": false
        },
        {
          "word_postproc": "decreased",
          "score": 0,
          "has_preceeding_space": true,
          "attach_to_next_token": false
        },
        {
          "word_postproc": "less than",
          "score": 0,
          "has_preceeding_space": true,
          "attach_to_next_token": false
        },
        {
          "word_postproc": "reduces",
          "score": 0,
          "has_preceeding_space": true,
          "attach_to_next_token": false
        }
      ],
      "srcunicodeoffsets": [
        {
          "begin": 0,
          "end": 9
        }
      ],
      "raw_src_segment": "လျော့နည်း",
      "start_pos": 0,
      "end_pos": 1
    }
  ],
  "confidence": 1,
  "ld_result": {
    "srclangs": [
      "my"
    ],
    "srclangs_confidences": [
      1
    ],
    "extended_srclangs": [
      "my"
    ]
  }
}
