{
  "sentences": [
    {
      "trans": "over",
      "orig": "စိုးအုပ်",
      "backend": 0
    },
    {
      "src_translit": "hcoe aote"
    }
  ],
  "src": "my",
  "alternative_translations": [
    {
      "src_phrase": "စိုး အုပ်",
      "alternative": [
        {
          "word_postproc": "over",
          "score": 995,
          "has_preceeding_space": true,
          "attach_to_next_token": false
        },
        {
          "word_postproc": "The chief official",
          "score": 2,
          "has_preceeding_space": true,
          "attach_to_next_token": false
        },
        {
          "word_postproc": "over the",
          "score": 1,
          "has_preceeding_space": true,
          "attach_to_next_token": false
        },
        {
          "word_postproc": "chief official",
          "score": 0,
          "has_preceeding_space": true,
          "attach_to_next_token": false
        }
      ],
      "srcunicodeoffsets": [
        {
          "begin": 0,
          "end": 8
        }
      ],
      "raw_src_segment": "စိုးအုပ်",
      "start_pos": 0,
      "end_pos": 1
    }
  ],
  "confidence": 1,
  "ld_result": {
    "srclangs": [
      "my"
    ],
    "srclangs_confidences": [
      1
    ],
    "extended_srclangs": [
      "my"
    ]
  }
}
