{
  "sentences": [
    {
      "trans": "a",
      "orig": "တစ်ရပ်",
      "backend": 0
    },
    {
      "src_translit": "taitraut"
    }
  ],
  "src": "my",
  "alternative_translations": [
    {
      "src_phrase": "တစ်ရပ်",
      "alternative": [
        {
          "word_postproc": "a",
          "score": 804,
          "has_preceeding_space": true,
          "attach_to_next_token": false
        },
        {
          "word_postproc": "an",
          "score": 194,
          "has_preceeding_space": true,
          "attach_to_next_token": false
        },
        {
          "word_postproc": "part",
          "score": 1,
          "has_preceeding_space": true,
          "attach_to_next_token": false
        },
        {
          "word_postproc": "term",
          "score": 0,
          "has_preceeding_space": true,
          "attach_to_next_token": false
        },
        {
          "word_postproc": "is an",
          "score": 0,
          "has_preceeding_space": true,
          "attach_to_next_token": false
        }
      ],
      "srcunicodeoffsets": [
        {
          "begin": 0,
          "end": 6
        }
      ],
      "raw_src_segment": "တစ်ရပ်",
      "start_pos": 0,
      "end_pos": 1
    }
  ],
  "confidence": 1,
  "ld_result": {
    "srclangs": [
      "my"
    ],
    "srclangs_confidences": [
      1
    ],
    "extended_srclangs": [
      "my"
    ]
  }
}
