{
  "sentences": [
    {
      "trans": "magic",
      "orig": "မျှော",
      "backend": 0
    },
    {
      "src_translit": "myahaaw"
    }
  ],
  "dict": [
    {
      "pos": "verb",
      "terms": [
        "set adrift",
        "let adrift",
        "give sbrope",
        "venture"
      ],
      "entry": [
        {
          "word": "set adrift",
          "score": 0.0083855102
        },
        {
          "word": "let adrift",
          "score": 0.0083855102
        },
        {
          "word": "give sbrope",
          "score": 0.0083855102
        },
        {
          "word": "venture",
          "score": 0.0083855102
        }
      ],
      "base_form": "မျှော",
      "pos_enum": 2
    }
  ],
  "src": "my",
  "alternative_translations": [
    {
      "src_phrase": "မျှော",
      "alternative": [
        {
          "word_postproc": "magic",
          "score": 1000,
          "has_preceeding_space": true,
          "attach_to_next_token": false
        },
        {
          "word_postproc": "give sbrope",
          "score": 0,
          "has_preceeding_space": true,
          "attach_to_next_token": false
        },
        {
          "word_postproc": "let adrift",
          "score": 0,
          "has_preceeding_space": true,
          "attach_to_next_token": false
        },
        {
          "word_postproc": "float",
          "score": 0,
          "has_preceeding_space": true,
          "attach_to_next_token": false
        },
        {
          "word_postproc": "interdepartmental circular",
          "score": 0,
          "has_preceeding_space": true,
          "attach_to_next_token": false
        }
      ],
      "srcunicodeoffsets": [
        {
          "begin": 0,
          "end": 5
        }
      ],
      "raw_src_segment": "မျှော",
      "start_pos": 0,
      "end_pos": 1
    }
  ],
  "confidence": 1,
  "ld_result": {
    "srclangs": [
      "my"
    ],
    "srclangs_confidences": [
      1
    ],
    "extended_srclangs": [
      "my"
    ]
  }
}
