{
  "sentences": [
    {
      "trans": "အောက်ခြေသိမ်း",
      "orig": "အောက်ခြေသိမ်း",
      "backend": 0
    },
    {
      "src_translit": "aouthkyaysaim"
    }
  ],
  "src": "my",
  "alternative_translations": [
    {
      "src_phrase": "အောက်ခြေသိမ်း",
      "alternative": [
        {
          "word_postproc": "အောက်ခြေသိမ်း",
          "score": 1000,
          "has_preceeding_space": true,
          "attach_to_next_token": false
        }
      ],
      "srcunicodeoffsets": [
        {
          "begin": 0,
          "end": 13
        }
      ],
      "raw_src_segment": "အောက်ခြေသိမ်း",
      "start_pos": 0,
      "end_pos": 1
    }
  ],
  "confidence": 1,
  "ld_result": {
    "srclangs": [
      "my"
    ],
    "srclangs_confidences": [
      1
    ],
    "extended_srclangs": [
      "my"
    ]
  }
}
