{
  "sentences": [
    {
      "trans": "Petty larceny",
      "orig": "ခိုးသေးမီးပွား",
      "backend": 0
    },
    {
      "src_translit": "hkoe sayy mee pwarr"
    }
  ],
  "dict": [
    {
      "pos": "noun",
      "terms": [
        "petty larceny"
      ],
      "entry": [
        {
          "word": "petty larceny"
        }
      ],
      "base_form": "ခိုးသေးမီးပွား",
      "pos_enum": 1
    }
  ],
  "src": "my",
  "alternative_translations": [
    {
      "src_phrase": "ခိုး သေး မီး ပွား",
      "alternative": [
        {
          "word_postproc": "Petty larceny",
          "score": 1000,
          "has_preceeding_space": true,
          "attach_to_next_token": false
        }
      ],
      "srcunicodeoffsets": [
        {
          "begin": 0,
          "end": 14
        }
      ],
      "raw_src_segment": "ခိုးသေးမီးပွား",
      "start_pos": 0,
      "end_pos": 2
    }
  ],
  "confidence": 1,
  "ld_result": {
    "srclangs": [
      "my"
    ],
    "srclangs_confidences": [
      1
    ],
    "extended_srclangs": [
      "my"
    ]
  }
}
