{
  "sentences": [
    {
      "trans": "small lobster",
      "orig": "ဆတ်ထုပ်",
      "backend": 0
    },
    {
      "src_translit": "saat htote"
    }
  ],
  "dict": [
    {
      "pos": "noun",
      "terms": [
        "small lobster"
      ],
      "entry": [
        {
          "word": "small lobster"
        }
      ],
      "base_form": "ဆတ်ထုပ်",
      "pos_enum": 1
    }
  ],
  "src": "my",
  "alternative_translations": [
    {
      "src_phrase": "ဆတ် ထုပ်",
      "alternative": [
        {
          "word_postproc": "small lobster",
          "score": 1000,
          "has_preceeding_space": true,
          "attach_to_next_token": false
        }
      ],
      "srcunicodeoffsets": [
        {
          "begin": 0,
          "end": 7
        }
      ],
      "raw_src_segment": "ဆတ်ထုပ်",
      "start_pos": 0,
      "end_pos": 2
    }
  ],
  "confidence": 1,
  "ld_result": {
    "srclangs": [
      "my"
    ],
    "srclangs_confidences": [
      1
    ],
    "extended_srclangs": [
      "my"
    ]
  }
}
